{
  "id": "halpern-murakozy-2009-efige-wp15",
  "title": "Price dispersion in trade with EU countries",
  "title_hu": null,
  "authors": [
    "halpern-laszlo",
    "murakozy-balazs"
  ],
  "outlet_kind": "working_paper",
  "outlet": "EFIGE Working Paper",
  "outlet_issue": "15",
  "institution": "Bruegel (EFIGE)",
  "year": 2009,
  "language": "en",
  "url": "https://bruegel.org/wp-content/uploads/2015/09/EFIGEWP15.pdf",
  "doi": null,
  "summary_en": null,
  "summary_hu": null,
  "policy_relevance": null,
  "policy_relevance_hu": null,
  "topics": [],
  "countries_studied": [],
  "policy_instruments": [],
  "linked_paper_id": null,
  "added_at": "2026-04-25",
  "last_reviewed_at": "2026-04-25",
  "review_status": "metadata-fetched"
}