{
  "id": "adamecz-adamecz-volgyi-et-al-2023-wmhp",
  "title": "Confidence in public institutions is critical in containing the COVID‐19 pandemic",
  "authors": [
    "adamecz-anna",
    "Anna Adamecz-Völgyi",
    "szabo-morvai-agnes"
  ],
  "publication_type": "article",
  "journal": "World Medical & Health Policy",
  "year": 2023,
  "volume": "15",
  "issue": "4",
  "pages": "553-569",
  "doi": "10.1002/wmh3.568",
  "working_paper_series": null,
  "url_published": "https://doi.org/10.1002/wmh3.568",
  "url_pdf": "https://onlinelibrary.wiley.com/doi/pdfdirect/10.1002/wmh3.568",
  "url_replication": null,
  "abstract": "Abstract This paper investigates the relative importance of confidence in public institutions to explain cross‐country differences in the severity of the coronavirus disease 2019 (COVID‐19) pandemic. We find that a 1 SD increase (e.g., the actual difference between the United States and Finland) in confidence is associated with 56.3% fewer predicted deaths per million inhabitants. Confidence in public institutions is one of the most important predictors of deaths attributed to COVID‐19, compared to country‐level measures of health risks, the health system, demographics, economic and political development, and social capital. We show for the first time that confidence in public institutions encompasses more than just the unobserved quality of health or public services in general. If confidence only included the perceived quality, it would be associated with other health and social outcomes such as breast cancer recovery rates or imprisonment as well, but this is not the case. Moreover, our results indicate that fighting a pandemic requires citizens to cooperate with their governments, and willingness to cooperate relies on confidence in public institutions.",
  "summary_en": null,
  "summary_hu": null,
  "data_used": null,
  "data_used_hu": null,
  "policy_relevance": null,
  "policy_relevance_hu": null,
  "topics": [],
  "methods": [],
  "countries_studied": [],
  "data_types": [],
  "featured": false,
  "added_at": "2026-04-22",
  "last_reviewed_at": "2026-04-22",
  "review_status": "metadata-fetched",
  "openalex_id": "W4365452052"
}