{
  "id": "ambrus-field-et-al-2010-qje",
  "title": "Muslim Family Law, Prenuptial Agreements, and the Emergence of Dowry in Bangladesh<sup>*</sup>",
  "authors": [
    "ambrus-attila",
    "Erica Field",
    "Máximo Torero"
  ],
  "publication_type": "article",
  "journal": "The Quarterly Journal of Economics",
  "year": 2010,
  "volume": "125",
  "issue": "3",
  "pages": "1349-1397",
  "doi": "10.1162/qjec.2010.125.3.1349",
  "working_paper_series": null,
  "url_published": "https://doi.org/10.1162/qjec.2010.125.3.1349",
  "url_pdf": null,
  "url_replication": null,
  "abstract": "We explain trends in dowry levels in Bangladesh by drawing attention to an institutional feature of marriage contracts previously ignored in the literature: mehr or traditional Islamic bride-price. We develop a model of marriage contracts in which mehr serves as a barrier to husbands exiting marriage and a component of dowry as an amount that ex ante compensates the groom for the cost of mehr. We investigate how mehr and dowry respond to exogenous changes in the costs of polygamy and divorce, and show that our model gives a different set of predictions than traditional models. We show that major changes in dowry levels took place precisely after the legal changes, corresponding to simultaneous changes in levels of mehr.",
  "summary_en": null,
  "summary_hu": null,
  "data_used": null,
  "data_used_hu": null,
  "policy_relevance": null,
  "policy_relevance_hu": null,
  "topics": [],
  "methods": [],
  "countries_studied": [],
  "data_types": [],
  "featured": false,
  "added_at": "2026-04-22",
  "last_reviewed_at": "2026-04-22",
  "review_status": "metadata-fetched",
  "openalex_id": "W2166543278"
}