{
  "url_pdf": null,
  "url_replication": null,
  "abstract": "",
  "summary_en": null,
  "summary_hu": null,
  "data_used": null,
  "data_used_hu": null,
  "policy_relevance": null,
  "policy_relevance_hu": null,
  "topics": [],
  "methods": [],
  "countries_studied": [],
  "data_types": [],
  "featured": false,
  "added_at": "2026-04-27",
  "last_reviewed_at": "2026-04-27",
  "review_status": "metadata-fetched",
  "policy_instruments": [],
  "working_paper_series": "KRTK-KTI Working Papers",
  "pages": null,
  "issue": null,
  "volume": null,
  "id": "baro-branyiczki-et-al-2022-krtkwp-payroll-taxes",
  "title": "Firm heterogeneity and the impact of payroll taxes",
  "authors": [
    "Anita Báró",
    "branyiczki-reka",
    "lindner-attila",
    "prinz-daniel",
    "Lóránt Márk"
  ],
  "publication_type": "working_paper",
  "journal": null,
  "year": 2022,
  "doi": null,
  "url_published": null
}