{
  "id": "benczur-ilut-2015-jeea",
  "title": "EVIDENCE FOR RELATIONAL CONTRACTS IN SOVEREIGN BANK LENDING",
  "authors": [
    "benczur-peter",
    "Cosmin Ilut"
  ],
  "publication_type": "article",
  "journal": "Journal of the European Economic Association",
  "year": 2015,
  "volume": "14",
  "issue": "2",
  "pages": "375-404",
  "doi": "10.1111/jeea.12151",
  "working_paper_series": null,
  "url_published": "https://doi.org/10.1111/jeea.12151",
  "url_pdf": null,
  "url_replication": null,
  "abstract": "This paper presents direct evidence for relational contracts in sovereign bank lending. Unlike the existing empirical literature, its instrumental variables method allows for distinguishing a direct influence of past repayment problems on current spreads (a “punishment” effect in prices) from an indirect effect through higher expected future default probabilities (“loss of reputation”). Such a punishment provides positive surplus to lenders after a default and decreases the borrower's present discounted value of the net benefits of future borrowing, which create dynamic incentives. Using data on bank loans to developing countries for 1973–1981 and constructing continuous variables for credit history, we find evidence that most of the influence of past repayment problems is through the direct, punishment channel.",
  "summary_en": null,
  "summary_hu": null,
  "data_used": null,
  "data_used_hu": null,
  "policy_relevance": null,
  "policy_relevance_hu": null,
  "topics": [],
  "methods": [],
  "countries_studied": [],
  "data_types": [],
  "featured": false,
  "added_at": "2026-04-22",
  "last_reviewed_at": "2026-04-22",
  "review_status": "metadata-fetched",
  "openalex_id": "W3096331461"
}