{
  "id": "biro-branyiczki-2022-ksz",
  "title": "Várakozások és viselkedések a koronavírus-járvány idején",
  "authors": [
    "biro-aniko",
    "branyiczki-reka"
  ],
  "publication_type": "article",
  "journal": "Közgazdasági Szemle",
  "year": 2022,
  "volume": "69",
  "issue": "11",
  "pages": "1324-1344",
  "doi": "10.18414/ksz.2022.11.1324",
  "working_paper_series": null,
  "url_published": "https://doi.org/10.18414/ksz.2022.11.1324",
  "url_pdf": null,
  "url_replication": null,
  "abstract": "Tanulmányunkban az 50 év feletti európai lakosság mintáján arra a kérdésre keressük a választ, hogy a pozitív várakozások milyen összefüggésben vannak az elővigyázatos viselkedéssel. A jövőre vonatkozó várakozások befolyásolhatják, hogy mennyire fontos az egészség megőrzése, érdemes-e a jelenben erőfeszítéseket tenni bizonytalan jövőbeli pozitív hatásokért. A kérdést a koronavírus-járvány idején, 2020 és 2021 nyarán készült Survey of Health, Ageing and Retirement (SHARE) telefonos adatfelvételére támaszkodva elemezzük. A maszkviselést, a távolságtartást és az oltási hajlandóságot vizsgáljuk a jövőre vonatkozó pozitív várakozások függvényében. Eredményeink azt mutatják, hogy az ötven év feletti lakosság pozitív várakozások esetén nagyobb eséllyel tesz óvintézkedéseket a koronavírus ellen.*&#13;\\nJournal of Economic Literature (JEL) kód: D84, I12.",
  "summary_en": null,
  "summary_hu": null,
  "data_used": null,
  "data_used_hu": null,
  "policy_relevance": null,
  "policy_relevance_hu": null,
  "topics": [],
  "methods": [],
  "countries_studied": [],
  "data_types": [],
  "featured": false,
  "added_at": "2026-04-23",
  "last_reviewed_at": "2026-04-23",
  "review_status": "metadata-fetched",
  "openalex_id": "W4309181480"
}