{
  "id": "bojnec-ferto-2011-appec",
  "title": "Complementarities of trade advantage and trade competitiveness measures",
  "authors": [
    "Štefan Bojnec",
    "ferto-imre"
  ],
  "publication_type": "article",
  "journal": "Applied Economics",
  "year": 2011,
  "volume": "44",
  "issue": "4",
  "pages": "399-408",
  "doi": "10.1080/00036846.2010.508725",
  "working_paper_series": null,
  "url_published": "https://doi.org/10.1080/00036846.2010.508725",
  "url_pdf": null,
  "url_replication": null,
  "abstract": "The complementarities of trade advantage and trade competitiveness measures for agro food trade of five Central European (CE-5) countries with the European Union are analysed. The stability and duration of the trade measures over time is investigated by the survival analysis using the nonparametric Kaplan–Meier product limit estimator, and the consistency test between the trade measures is conducted by the stratified Cox proportional hazard model. The CE-5 countries experienced a greater number of products with relative trade disadvantages and greater significance of one way imports. Unlike the Czech Republic, Poland, Slovakia and Slovenia, Hungary experienced Relative Trade Advantages (RTAs) for bulk raw commodities, processed intermediates and horticulture, with the greatest significance of successful quality competition and one-way exports, and the lowest significance of unsuccessful price and unsuccessful quality competition. The duration of RTAs is longer than the duration for the successful trade competition categories. Our results confirm that the RTA is consistent with the one way export and the successful price and successful quality competition categories in two way trade on one side, and the relative trade disadvantage with the one way import and the unsuccessful price and unsuccessful quality competition on the other.",
  "summary_en": null,
  "summary_hu": null,
  "data_used": null,
  "data_used_hu": null,
  "policy_relevance": null,
  "policy_relevance_hu": null,
  "topics": [],
  "methods": [],
  "countries_studied": [],
  "data_types": [],
  "featured": false,
  "added_at": "2026-04-23",
  "last_reviewed_at": "2026-04-23",
  "review_status": "metadata-fetched",
  "openalex_id": "W2052837055"
}