{
  "id": "branyiczki-2016-tr",
  "title": "Háztartások munkaintenzitása a válság idején és a kilábalás időszakában",
  "authors": [
    "branyiczki-reka"
  ],
  "publication_type": "chapter",
  "journal": "Társadalmi riport",
  "year": 2016,
  "volume": null,
  "issue": null,
  "pages": "217-239",
  "doi": "10.61501/trip.2016.11",
  "working_paper_series": null,
  "url_published": "https://doi.org/10.61501/trip.2016.11",
  "url_pdf": null,
  "url_replication": null,
  "abstract": null,
  "summary_en": null,
  "summary_hu": null,
  "data_used": null,
  "data_used_hu": null,
  "policy_relevance": null,
  "policy_relevance_hu": null,
  "topics": [],
  "methods": [],
  "countries_studied": [],
  "data_types": [],
  "featured": false,
  "added_at": "2026-04-23",
  "last_reviewed_at": "2026-04-23",
  "review_status": "metadata-fetched",
  "openalex_id": "W4388319893"
}