{
  "id": "csoka-hever-2018-frl",
  "title": "Portfolio valuation under liquidity constraints with permanent price impact",
  "authors": [
    "csoka-peter",
    "Judit Hevér"
  ],
  "publication_type": "article",
  "journal": "Finance research letters",
  "year": 2018,
  "volume": "26",
  "issue": null,
  "pages": "235-241",
  "doi": "10.1016/j.frl.2018.02.019",
  "working_paper_series": null,
  "url_published": "https://doi.org/10.1016/j.frl.2018.02.019",
  "url_pdf": null,
  "url_replication": null,
  "abstract": null,
  "summary_en": null,
  "summary_hu": null,
  "data_used": null,
  "data_used_hu": null,
  "policy_relevance": null,
  "policy_relevance_hu": null,
  "topics": [],
  "methods": [],
  "countries_studied": [],
  "data_types": [],
  "featured": false,
  "added_at": "2026-04-22",
  "last_reviewed_at": "2026-04-22",
  "review_status": "metadata-fetched",
  "openalex_id": "W2792848946"
}