{
  "id": "elek-drysdale-et-al-2018-ape",
  "title": "China and the global trading system: Then and now",
  "authors": [
    "elek-peter",
    "Peter Drysdale",
    "Samuel Hardwick"
  ],
  "publication_type": "chapter",
  "journal": "ANU Press eBooks",
  "year": 2018,
  "volume": null,
  "issue": null,
  "pages": "545-574",
  "doi": "10.22459/cyrd.07.2018.27",
  "working_paper_series": null,
  "url_published": "https://doi.org/10.22459/cyrd.07.2018.27",
  "url_pdf": "https://doi.org/10.22459/cyrd.07.2018.27",
  "url_replication": null,
  "abstract": null,
  "summary_en": null,
  "summary_hu": null,
  "data_used": null,
  "data_used_hu": null,
  "policy_relevance": null,
  "policy_relevance_hu": null,
  "topics": [],
  "methods": [],
  "countries_studied": [],
  "data_types": [],
  "featured": false,
  "added_at": "2026-04-23",
  "last_reviewed_at": "2026-04-23",
  "review_status": "metadata-fetched",
  "openalex_id": "W2883254434"
}