{
  "id": "heidhues-koster-et-al-2023-ej",
  "title": "Steering Fallible Consumers",
  "authors": [
    "Paul Heidhues",
    "Mats Köster",
    "koszegi-botond"
  ],
  "publication_type": "article",
  "journal": "The Economic Journal",
  "year": 2023,
  "volume": "133",
  "issue": "652",
  "pages": "1430-1465",
  "doi": "10.1093/ej/ueac093",
  "working_paper_series": null,
  "url_published": "https://doi.org/10.1093/ej/ueac093",
  "url_pdf": null,
  "url_replication": null,
  "abstract": "Abstract Online intermediaries with information about a consumer’s tendencies often ‘steer’ her toward products she is more likely to purchase. We analyse the welfare implications of this practice for ‘fallible’ consumers, who make statistical and strategic mistakes in evaluating offers. The welfare effects depend on the nature and quality of the intermediary’s information and on properties of the consumer’s mistakes. In particular, steering based on high-quality information about the consumer’s mistakes is typically harmful, sometimes extremely so. We argue that much real-life steering is of this type, raising the scope for a broader regulation of steering practices.",
  "summary_en": null,
  "summary_hu": null,
  "data_used": null,
  "data_used_hu": null,
  "policy_relevance": null,
  "policy_relevance_hu": null,
  "topics": [],
  "methods": [],
  "countries_studied": [],
  "data_types": [],
  "featured": false,
  "added_at": "2026-04-22",
  "last_reviewed_at": "2026-04-22",
  "review_status": "metadata-fetched",
  "openalex_id": "W4320886430"
}