{
  "id": "herrendorf-valentinyi-2022-em",
  "title": "Endogenous sector–biased technological change and industrial policy",
  "authors": [
    "Berthold Herrendorf",
    "valentinyi-akos"
  ],
  "publication_type": "article",
  "journal": "Economic Modelling",
  "year": 2022,
  "volume": "113",
  "issue": null,
  "pages": "105875-105875",
  "doi": "10.1016/j.econmod.2022.105875",
  "working_paper_series": null,
  "url_published": "https://doi.org/10.1016/j.econmod.2022.105875",
  "url_pdf": null,
  "url_replication": null,
  "abstract": "We build a model of structural transformation with endogenous sector–biased technological change. We show that if the return to specialization is larger in the goods sector than in the service sector, then the equilibrium has the following properties: aggregate growth is balanced; the service sector receives more innovation but the goods sector experiences more productivity growth; structural transformation takes place from goods to services. Compared to the efficient allocation the laissez–faire equilibrium has too much labor in the goods sector, implying that optimal industrial policy should aim to increase, not decrease, the pace of structural transformation.",
  "summary_en": null,
  "summary_hu": null,
  "data_used": null,
  "data_used_hu": null,
  "policy_relevance": null,
  "policy_relevance_hu": null,
  "topics": [],
  "methods": [],
  "countries_studied": [],
  "data_types": [],
  "featured": false,
  "added_at": "2026-04-22",
  "last_reviewed_at": "2026-04-22",
  "review_status": "metadata-fetched",
  "openalex_id": "W2212142548"
}