{
  "id": "kondor-2008-mp",
  "title": "The more we know, the less we agree: Higher-order expectations and public announcements",
  "authors": [
    "kondor-peter"
  ],
  "publication_type": "article",
  "journal": "2009 Meeting Papers",
  "year": 2008,
  "volume": null,
  "issue": null,
  "pages": null,
  "doi": null,
  "working_paper_series": null,
  "url_published": null,
  "url_pdf": null,
  "url_replication": null,
  "abstract": "Polarization of opinions after public announcement is widely observed, but often considered to be inconsistent with Bayesian learning. I show that this is not the case in environments where higher-order expectations play a role. I characterize informational structures where public announcement leads to polarization in all higher-order expectations, but not in first-order expectations. To illustrate the economic consequences, I modify two workhorse models of asymmetric information. I show in a Morris-Shin(1998) model that more disclosure of public information can increase the chance of successful currency attacks. I show in a dynamic Grossman-Stiglitz(1980) model that hectic trading around public announcements is consistent with common priors and Bayesian learning.",
  "summary_en": null,
  "summary_hu": null,
  "data_used": null,
  "data_used_hu": null,
  "policy_relevance": null,
  "policy_relevance_hu": null,
  "topics": [],
  "methods": [],
  "countries_studied": [],
  "data_types": [],
  "featured": false,
  "added_at": "2026-04-22",
  "last_reviewed_at": "2026-04-22",
  "review_status": "metadata-fetched",
  "openalex_id": "W1519315823"
}