{
  "id": "temesvary-2018-jfs",
  "title": "The transmission of foreign monetary policy shocks into the United States through foreign banks",
  "authors": [
    "temesvary-judit"
  ],
  "publication_type": "article",
  "journal": "Journal of Financial Stability",
  "year": 2018,
  "volume": "39",
  "issue": null,
  "pages": "104-124",
  "doi": "10.1016/j.jfs.2018.09.003",
  "working_paper_series": null,
  "url_published": "https://doi.org/10.1016/j.jfs.2018.09.003",
  "url_pdf": null,
  "url_replication": null,
  "abstract": null,
  "summary_en": null,
  "summary_hu": null,
  "data_used": null,
  "data_used_hu": null,
  "policy_relevance": null,
  "policy_relevance_hu": null,
  "topics": [],
  "methods": [],
  "countries_studied": [],
  "data_types": [],
  "featured": false,
  "added_at": "2026-04-24",
  "last_reviewed_at": "2026-04-24",
  "review_status": "metadata-fetched",
  "openalex_id": "W3121926918"
}